README
setup.py
awesomestream/__init__.py
awesomestream/backends.py
awesomestream/jsonrpc.py
awesomestream/utils.py
awesomestream.egg-info/PKG-INFO
awesomestream.egg-info/SOURCES.txt
awesomestream.egg-info/dependency_links.txt
awesomestream.egg-info/not-zip-safe
awesomestream.egg-info/requires.txt
awesomestream.egg-info/top_level.txt
tests/__init__.py
tests/test_backend.py
tests/test_utils.py