Metadata-Version: 1.0
Name: awesomestream
Version: 0.1
Summary: AwesomeStream makes awesome streams
Home-page: http://github.com/ericflo/awesomestream
Author: Eric Florenzano
Author-email: floguy@gmail.com
License: BSD
Keywords: json-rpc,stream,feed,werkzeug,cherrypy,sqlalchemy,redis
Platform: UNKNOWN
Classifier: Programming Language :: Python
Classifier: Topic :: Software Development :: Libraries :: Python Modules
Classifier: Environment :: Web Environment
